[
  {
    "timings": [
      {
        "metric": "interactive",
        "budget": 9000
      },
      {
        "metric": "first-meaningful-paint",
        "budget": 9000
      }
    ],
    "resourceSizes": [
      {
        "resourceType": "script",
        "budget": 1000
      },
      {
        "resourceType": "image",
        "budget": 1000
      },
      {
        "resourceType": "total",
        "budget": 1000
      }
    ],
    "resourceCounts": [
      {
        "resourceType": "total",
        "budget": 25
      }
    ]
  }
]
